{
    "Moonstone": {
        "properties": "new beginnings",
        "source": "Current Inventory",
        "reason": "Used for new beginnings, inner growth, and soothing emotional stress."
    },
    "Amethyst": {
        "properties": "intuition, peace",
        "source": "Current Inventory",
        "reason": "Used for intuition, spiritual protection, and calming the mind."
    },
    "Rose Quartz": {
        "properties": "compassion, love, self-love",
        "source": "Current Inventory",
        "reason": "Used for unconditional love, deep inner healing, and peace."
    },
    "White Quartz": {
        "properties": "grounding",
        "source": "Current Inventory",
        "reason": "Used for amplifying energy, clarity of thought, and spiritual growth."
    },
    "Jade Beads": {
        "properties": "balance",
        "source": "Current Inventory",
        "reason": "Used for luck, friendship, and promoting self-sufficiency."
    },
    "Green Aventurine": {
        "properties": "opportunity, optimism",
        "source": "Current Inventory",
        "reason": "Used for manifesting prosperity, wealth, and winning energy."
    },
    "Malachite": {
        "properties": "transformation",
        "source": "Current Inventory",
        "reason": "Used for deep energy cleansing and bringing positive transformation."
    },
    "Obsidian": {
        "properties": "grounding",
        "source": "Current Inventory",
        "reason": "Used for forming a shield against negativity and providing deep grounding."
    },
    "Grey Agate": {
        "properties": "grounding",
        "source": "Current Inventory",
        "reason": "Used for grounding, emotional stability, and self-confidence."
    },
    "Clear Quartz": {
        "properties": "grounding",
        "source": "Current Inventory",
        "reason": "Used for focus, clarity, and amplifying the energy of other stones."
    },
    "Light Amethyst": {
        "properties": "dreaming",
        "source": "Current Inventory",
        "reason": "Used for balancing energy and spiritual grounding."
    },
    "Amethyst Cluster": {
        "properties": "grounding",
        "source": "Current Inventory",
        "reason": "Used for balancing energy and spiritual grounding."
    },
    "Dark Amethyst": {
        "properties": "sobriety",
        "source": "Current Inventory",
        "reason": "Used for balancing energy and spiritual grounding."
    },
    "Driftwood": {
        "properties": "grounding",
        "source": "Current Inventory",
        "reason": "Used for balancing energy and spiritual grounding."
    },
    "Turquoise Beads": {
        "properties": "communication",
        "source": "Current Inventory",
        "reason": "Used for balancing energy and spiritual grounding."
    },
    "Pink Wire": {
        "properties": "grounding",
        "source": "Current Inventory",
        "reason": "Used for balancing energy and spiritual grounding."
    },
    "Rose Quartz Hearts": {
        "properties": "compassion, healing",
        "source": "Current Inventory",
        "reason": "Used for balancing energy and spiritual grounding."
    },
    "Quartz": {
        "properties": "grounding",
        "source": "Current Inventory",
        "reason": "Used for balancing energy and spiritual grounding."
    },
    "Sodalite": {
        "properties": "focus",
        "source": "Current Inventory",
        "reason": "Used for logic, emotional balance, and intuition."
    },
    "Black Wire": {
        "properties": "grounding",
        "source": "Current Inventory",
        "reason": "Used for balancing energy and spiritual grounding."
    },
    "Tiger Eye Chips": {
        "properties": "protection",
        "source": "Current Inventory",
        "reason": "Used for balancing energy and spiritual grounding."
    },
    "Purple Wire": {
        "properties": "grounding",
        "source": "Current Inventory",
        "reason": "Used for balancing energy and spiritual grounding."
    },
    "Magenta Agate": {
        "properties": "playful",
        "source": "Current Inventory",
        "reason": "Used for balancing energy and spiritual grounding."
    },
    "Raw Green Jade": {
        "properties": "grounding",
        "source": "Current Inventory",
        "reason": "Used for balancing energy and spiritual grounding."
    },
    "Genuine Malachite": {
        "properties": "abundance",
        "source": "Current Inventory",
        "reason": "Used for balancing energy and spiritual grounding."
    },
    "Cherry Quartz": {
        "properties": "beginnings",
        "source": "Current Inventory",
        "reason": "Used for balancing energy and spiritual grounding."
    },
    "Raw Rose Quartz": {
        "properties": "grounding",
        "source": "Current Inventory",
        "reason": "Used for balancing energy and spiritual grounding."
    },
    "Sunstone": {
        "properties": "grounding",
        "source": "Current Inventory",
        "reason": "Used for leadership and good fortune."
    },
    "Carnelian": {
        "properties": "confidence, grounding",
        "source": "Current Inventory",
        "reason": "Used for motivation, endurance, and leadership."
    },
    "Jasper": {
        "properties": "grounding, nurturing",
        "source": "Current Inventory",
        "reason": "Used for balancing energy and spiritual grounding."
    },
    "Unakite": {
        "properties": "balance, vision",
        "source": "Current Inventory",
        "reason": "Used for balancing energy and spiritual grounding."
    },
    "Sea Glass": {
        "properties": "grounding",
        "source": "Current Inventory",
        "reason": "Used for balancing energy and spiritual grounding."
    },
    "Aquamarine": {
        "properties": "tranquility",
        "source": "Current Inventory",
        "reason": "Used for balancing energy and spiritual grounding."
    },
    "Red Jasper": {
        "properties": "vitality",
        "source": "Current Inventory",
        "reason": "Used for balancing energy and spiritual grounding."
    },
    "Wire Root": {
        "properties": "grounding stability",
        "source": "Current Inventory",
        "reason": "Used for balancing energy and spiritual grounding."
    },
    "Agate": {
        "properties": "grounding",
        "source": "Current Inventory",
        "reason": "Used for balancing energy and spiritual grounding."
    },
    "Clear Quartz Point": {
        "properties": "grounding",
        "source": "Current Inventory",
        "reason": "Used for balancing energy and spiritual grounding."
    },
    "Amethyst Chips": {
        "properties": "amplification",
        "source": "Current Inventory",
        "reason": "Used for balancing energy and spiritual grounding."
    },
    "Fluorite": {
        "properties": "grounding",
        "source": "Current Inventory",
        "reason": "Used for focus and clearing the mind."
    },
    "Jade": {
        "properties": "luck, prosperity",
        "source": "Current Inventory",
        "reason": "Used for balancing energy and spiritual grounding."
    },
    "Sodalite Chips": {
        "properties": "logic",
        "source": "Current Inventory",
        "reason": "Used for balancing energy and spiritual grounding."
    }
}